pyktx2/__init__.py
pyktx2/_version.py
pyktx2/parser.py
pyktx2/viewer/__init__.py
pyktx2/viewer/__main__.py
pyktx2/viewer/image_viewer.py
tests/test_ktx2.py
pyktx2-0.3.1.dist-info/LICENSE
pyktx2-0.3.1.dist-info/METADATA
pyktx2-0.3.1.dist-info/WHEEL
pyktx2-0.3.1.dist-info/entry_points.txt
pyktx2-0.3.1.dist-info/top_level.txt
pyktx2-0.3.1.dist-info/RECORD
